django_fullstack/__init__.py
django_fullstack/__main__.py
django_fullstack/apps.py
django_fullstack/core/__init__.py
django_fullstack/core/handlers/__init__.py
django_fullstack/core/handlers/files.py
django_fullstack/core/management/__init__.py
django_fullstack/core/management/commands/_remove-app.py
django_fullstack/core/management/commands/create-app.py
django_fullstack/core/management/commands/startapp.py
django_fullstack/core/management/commands/startproject.py
django_fullstack/core/utils.py
django_fullstack/django_vite/__init__.py
django_fullstack/django_vite/apps.py
django_fullstack/django_vite/core/__init__.py
django_fullstack/django_vite/core/asset_loader.py
django_fullstack/django_vite/core/exceptions.py
django_fullstack/django_vite/core/tag_generator.py
django_fullstack/django_vite/templatetags/__init__.py
django_fullstack/django_vite/templatetags/django_vite.py
django_fullstack/inertia/__init__.py
django_fullstack/inertia/http.py
django_fullstack/inertia/middleware.py
django_fullstack/inertia/settings.py
django_fullstack/inertia/share.py
django_fullstack/inertia/templates/inertia.html
django_fullstack/inertia/templates/inertia_ssr.html
django_fullstack/inertia/test.py
django_fullstack/inertia/tests/__init__.py
django_fullstack/inertia/tests/settings.py
django_fullstack/inertia/tests/test_encoder.py
django_fullstack/inertia/tests/test_middleware.py
django_fullstack/inertia/tests/test_rendering.py
django_fullstack/inertia/tests/test_settings.py
django_fullstack/inertia/tests/test_ssr.py
django_fullstack/inertia/tests/test_tests.py
django_fullstack/inertia/tests/testapp/apps.py
django_fullstack/inertia/tests/testapp/layout.html
django_fullstack/inertia/tests/testapp/models.py
django_fullstack/inertia/tests/testapp/urls.py
django_fullstack/inertia/tests/testapp/views.py
django_fullstack/inertia/utils.py
django_fullstack/middleware.py
django_fullstack/scripts/django_fullstack.py
django_fullstack/settings.py
django_fullstack/static/dist/vite.svg
django_fullstack-1.0.0.dist-info/entry_points.txt
django_fullstack-1.0.0.dist-info/WHEEL
django_fullstack-1.0.0.dist-info/METADATA
django_fullstack-1.0.0.dist-info/RECORD
