Metadata-Version: 2.1
Name: django-fullstack
Version: 1.0.0
Summary: make your project frontend + django with django-fullstack, it's so easy
Home-page: https://github.com/rajasunrise/django-fullstack
License: MIT
Keywords: django-fullstack,react,vitejs,vue,django
Author: Raja Sunrise
Author-email: rajasunsrise@gmail.com
Requires-Python: >=3.9,<3.13
Classifier: Framework :: Django :: 4.0
Classifier: Framework :: Django :: 4.1
Classifier: Framework :: Django :: 4.2
Classifier: Framework :: Django :: 5.0
Classifier: License :: OSI Approved :: MIT License
Classifier: Programming Language :: Python :: 3
Classifier: Programming Language :: Python :: 3.10
Classifier: Programming Language :: Python :: 3.11
Classifier: Programming Language :: Python :: 3.12
Classifier: Programming Language :: Python :: 3.9
Classifier: Topic :: Utilities
Requires-Dist: Django (>=3.0,<6.0)
Requires-Dist: requests (>=2.28.2,<2.40.0)
Project-URL: Repository, https://github.com/rajasunrise/django-fullstack
